proxy_fleet/__init__.py
proxy_fleet/cli/__init__.py
proxy_fleet/cli/main.py
proxy_fleet/core/__init__.py
proxy_fleet/core/fleet.py
proxy_fleet/models/__init__.py
proxy_fleet/models/config.py
proxy_fleet/models/proxy.py
proxy_fleet/models/task.py
proxy_fleet/server/__init__.py
proxy_fleet/server/config.py
proxy_fleet/server/enhanced_proxy_server.py
proxy_fleet/server/proxy_server.py
proxy_fleet/server/selector.py
proxy_fleet/utils/__init__.py
proxy_fleet/utils/output.py
proxy_fleet/utils/proxy_utils.py
proxy_fleet/utils/socks_validator.py
proxy_fleet-2.1.2.dist-info/licenses/LICENSE
proxy_fleet-2.1.2.dist-info/METADATA
proxy_fleet-2.1.2.dist-info/WHEEL
proxy_fleet-2.1.2.dist-info/entry_points.txt
proxy_fleet-2.1.2.dist-info/top_level.txt
proxy_fleet-2.1.2.dist-info/RECORD
