Metadata-Version: 2.4
Name: proxy-fleet
Version: 2.1.2
Summary: A production-ready proxy server with intelligent load balancing and health monitoring
Home-page: https://github.com/changyy/py-proxy-fleet
Author: changyy
Author-email: changyy.csie@gmail.com
Project-URL: Bug Reports, https://github.com/changyy/py-proxy-fleet/issues
Project-URL: Source, https://github.com/changyy/py-proxy-fleet
Project-URL: Documentation, https://github.com/changyy/py-proxy-fleet/blob/main/docs/README.md
Keywords: proxy,proxy-server,load-balancer,haproxy,nginx,health-check,failover,rotation,socks,http-proxy,networking,async,aiohttp,monitoring,graceful-shutdown
Classifier: Development Status :: 5 - Production/Stable
Classifier: Intended Audience :: Developers
Classifier: Intended Audience :: System Administrators
Classifier: Topic :: Internet :: Proxy Servers
Classifier: Topic :: Internet :: WWW/HTTP :: HTTP Servers
Classifier: Topic :: System :: Networking
Classifier: Topic :: Software Development :: Libraries :: Python Modules
Classifier: License :: OSI Approved :: MIT License
Classifier: License :: OSI Approved :: MIT License
Classifier: Programming Language :: Python :: 3
Classifier: Programming Language :: Python :: 3.8
Classifier: Programming Language :: Python :: 3.9
Classifier: Programming Language :: Python :: 3.10
Classifier: Programming Language :: Python :: 3.11
Classifier: Programming Language :: Python :: 3.12
Classifier: Operating System :: OS Independent
Classifier: Environment :: Console
Classifier: Framework :: AsyncIO
Requires-Python: >=3.8
License-File: LICENSE
Requires-Dist: aiohttp<4.0.0,>=3.8.0
Requires-Dist: aiohttp-socks<1.0.0,>=0.7.0
Requires-Dist: click<9.0.0,>=8.0.0
Requires-Dist: pydantic<3.0.0,>=2.0.0
Provides-Extra: dev
Requires-Dist: pytest>=7.0.0; extra == "dev"
Requires-Dist: pytest-asyncio>=0.21.0; extra == "dev"
Requires-Dist: pytest-cov>=4.0.0; extra == "dev"
Requires-Dist: black>=22.0.0; extra == "dev"
Requires-Dist: isort>=5.0.0; extra == "dev"
Requires-Dist: flake8>=5.0.0; extra == "dev"
Requires-Dist: mypy>=0.991; extra == "dev"
Requires-Dist: pre-commit>=2.20.0; extra == "dev"
Provides-Extra: test
Requires-Dist: pytest>=7.0.0; extra == "test"
Requires-Dist: pytest-asyncio>=0.21.0; extra == "test"
Requires-Dist: pytest-cov>=4.0.0; extra == "test"
Provides-Extra: monitoring
Requires-Dist: prometheus-client>=0.14.0; extra == "monitoring"
Requires-Dist: psutil>=5.9.0; extra == "monitoring"
Provides-Extra: all
Requires-Dist: pytest>=7.0.0; extra == "all"
Requires-Dist: pytest-asyncio>=0.21.0; extra == "all"
Requires-Dist: pytest-cov>=4.0.0; extra == "all"
Requires-Dist: black>=22.0.0; extra == "all"
Requires-Dist: flake8>=5.0.0; extra == "all"
Requires-Dist: mypy>=0.991; extra == "all"
Requires-Dist: pre-commit>=2.20.0; extra == "all"
Requires-Dist: prometheus-client>=0.14.0; extra == "all"
Requires-Dist: psutil>=5.9.0; extra == "all"
Dynamic: author
Dynamic: author-email
Dynamic: classifier
Dynamic: description
Dynamic: description-content-type
Dynamic: home-page
Dynamic: keywords
Dynamic: license-file
Dynamic: project-url
Dynamic: provides-extra
Dynamic: requires-dist
Dynamic: requires-python
Dynamic: summary
